victor86c_parser/__init__.py
victor86c_parser/parser.py
victor86c_parser-1.0.2.dist-info/METADATA
victor86c_parser-1.0.2.dist-info/WHEEL
victor86c_parser-1.0.2.dist-info/top_level.txt
victor86c_parser-1.0.2.dist-info/RECORD
