Metadata-Version: 2.4
Name: victor86c_parser
Version: 1.0.2
Summary: Biblioteca Python para decodificar o protocolo de comunicação serial do multímetro VICTOR 86C/86D.
Home-page: https://github.com/Gungsu/victor86c_library
Author: Amauri B. M. de Deus
Author-email: adeus.sjp@gmail.com
Project-URL: Bug Tracker, https://github.com/Gungsu/victor86c_library/issues
Project-URL: Source Code, https://github.com/Gungsu/victor86c_library
Keywords: multimeter,victor86c,victor86d,serial,dmm,instrumentation,automation,hardware
Classifier: Development Status :: 4 - Beta
Classifier: Intended Audience :: Developers
Classifier: Topic :: Software Development :: Libraries :: Python Modules
Classifier: Programming Language :: Python :: 3
Classifier: License :: OSI Approved :: MIT License
Classifier: Operating System :: OS Independent
Requires-Python: >=3.6
Dynamic: author
Dynamic: author-email
Dynamic: classifier
Dynamic: description
Dynamic: description-content-type
Dynamic: home-page
Dynamic: keywords
Dynamic: project-url
Dynamic: requires-python
Dynamic: summary
